{"GOOGL": {"2022-11-04": {"Open": 83.68, "High": 86.75, "Low": 83.222, "Close": 86.53}, "2022-11-03": {"Open": 87.04, "High": 87.97, "Low": 83.34, "Close": 83.68}, "2022-11-02": {"Open": 90.58, "High": 91.35, "Low": 86.74, "Close": 87.04}, "2022-11-01": {"Open": 94.8, "High": 96.03, "Low": 90.26, "Close": 90.58}, "2022-10-31": {"Open": 96.33, "High": 97.03, "Low": 93.98, "Close": 94.8}, "2022-10-28": {"Open": 92.0, "High": 96.55, "Low": 91.64, "Close": 96.33}, "2022-10-27": {"Open": 95.35, "High": 95.73, "Low": 90.38, "Close": 92.0}, "2022-10-26": {"Open": 97.6001, "High": 98.7, "Low": 94.35, "Close": 95.35}, "2022-10-25": {"Open": 102.9, "High": 104.82, "Low": 96.71, "Close": 97.6001}, "2022-10-24": {"Open": 101.22, "High": 102.97, "Low": 99.98, "Close": 102.9}, "2022-10-21": {"Open": 98.09, "High": 102.0, "Low": 97.65, "Close": 101.22}, "2022-10-20": {"Open": 99.58, "High": 102.32, "Low": 96.98, "Close": 98.09}, "2022-10-19": {"Open": 102.44, "High": 101.8, "Low": 98.84, "Close": 99.58}, "2022-10-18": {"Open": 101.3, "High": 103.47, "Low": 99.721, "Close": 102.44}, "2022-10-17": {"Open": 96.3, "High": 101.99, "Low": 96.319, "Close": 101.3}, "2022-10-14": {"Open": 98.89, "High": 101.14, "Low": 96.3, "Close": 96.3}, "2022-10-13": {"Open": 97.8, "High": 99.775, "Low": 94.0, "Close": 98.89}, "2022-10-12": {"Open": 97.3, "High": 98.75, "Low": 96.63, "Close": 97.8}, "2022-10-11": {"Open": 98.05, "High": 99.245, "Low": 96.31, "Close": 97.3}, "2022-10-10": {"Open": 98.72, "High": 99.27, "Low": 96.69, "Close": 98.05}, "2022-10-07": {"Open": 101.02, "High": 101.73, "Low": 97.8, "Close": 98.72}, "2022-10-06": {"Open": 101.91, "High": 102.9254, "Low": 100.31, "Close": 101.02}, "2022-10-05": {"Open": 101.25, "High": 102.16, "Low": 98.8, "Close": 101.91}, "2022-10-04": {"Open": 99.18, "High": 101.84, "Low": 98.394, "Close": 101.25}, "2022-10-03": {"Open": 95.81, "High": 100.68, "Low": 95.1615, "Close": 99.18}, "2022-09-30": {"Open": 97.87, "High": 98.9, "Low": 95.12, "Close": 95.81}, "2022-09-29": {"Open": 99.94, "High": 99.8, "Low": 95.96, "Close": 97.87}, "2022-09-28": {"Open": 97.5, "High": 100.7, "Low": 96.29, "Close": 99.94}, "2022-09-27": {"Open": 98.5, "High": 100.0, "Low": 95.69, "Close": 97.5}}, "META": {"2022-11-04": {"Open": 88.79, "High": 91.39, "Low": 88.09, "Close": 90.65}, "2022-11-03": {"Open": 90.7, "High": 91.94, "Low": 88.41, "Close": 88.79}, "2022-11-02": {"Open": 94.75, "High": 95.93, "Low": 90.27, "Close": 90.7}, "2022-11-01": {"Open": 93.26, "High": 97.49, "Low": 93.55, "Close": 94.75}, "2022-10-31": {"Open": 98.9, "High": 99.8, "Low": 92.6, "Close": 93.26}, "2022-10-28": {"Open": 97.83, "High": 100.85, "Low": 96.78, "Close": 98.9}, "2022-10-27": {"Open": 104.3, "High": 109.46, "Low": 96.1, "Close": 97.83}, "2022-10-26": {"Open": 132.0, "High": 142.6, "Low": 103.8, "Close": 104.3}, "2022-10-25": {"Open": 129.83, "High": 138.35, "Low": 128.89, "Close": 132.0}, "2022-10-24": {"Open": 130.32, "High": 133.48, "Low": 124.57, "Close": 129.83}, "2022-10-21": {"Open": 126.25, "High": 131.202, "Low": 125.44, "Close": 130.32}, "2022-10-20": {"Open": 132.5, "High": 136.77, "Low": 124.67, "Close": 126.25}, "2022-10-19": {"Open": 135.9, "High": 137.0, "Low": 132.19, "Close": 132.5}, "2022-10-18": {"Open": 135.61, "High": 137.8399, "Low": 131.4, "Close": 135.9}, "2022-10-17": {"Open": 126.34, "High": 135.71, "Low": 126.03, "Close": 135.61}, "2022-10-14": {"Open": 130.15, "High": 132.7, "Low": 126.0, "Close": 126.34}, "2022-10-13": {"Open": 127.59, "High": 131.14, "Low": 122.5301, "Close": 130.15}, "2022-10-12": {"Open": 128.75, "High": 130.5585, "Low": 126.25, "Close": 127.59}, "2022-10-11": {"Open": 134.29, "High": 132.66, "Low": 126.99, "Close": 128.75}, "2022-10-10": {"Open": 133.11, "High": 136.11, "Low": 131.39, "Close": 134.29}, "2022-10-07": {"Open": 138.4, "High": 140.12, "Low": 132.44, "Close": 133.11}, "2022-10-06": {"Open": 139.98, "High": 141.45, "Low": 136.6, "Close": 138.4}, "2022-10-05": {"Open": 140.24, "High": 140.45, "Low": 134.78, "Close": 139.98}, "2022-10-04": {"Open": 139.1, "High": 142.3901, "Low": 139.0, "Close": 140.24}, "2022-10-03": {"Open": 136.06, "High": 139.62, "Low": 135.03, "Close": 139.1}, "2022-09-30": {"Open": 136.83, "High": 140.99, "Low": 135.5, "Close": 136.06}, "2022-09-29": {"Open": 141.14, "High": 141.256, "Low": 135.2, "Close": 136.83}, "2022-09-28": {"Open": 134.71, "High": 142.03, "Low": 132.01, "Close": 141.14}, "2022-09-27": {"Open": 136.33, "High": 139.42, "Low": 132.86, "Close": 134.71}}, "AAPL": {"2022-11-04": {"Open": 137.5015, "High": 142.67, "Low": 134.38, "Close": 138.12}, "2022-11-03": {"Open": 143.8609, "High": 144.6795, "Low": 137.172, "Close": 137.5015}, "2022-11-02": {"Open": 150.1604, "High": 151.9175, "Low": 143.8509, "Close": 143.8609}, "2022-11-01": {"Open": 153.2054, "High": 155.3918, "Low": 148.8825, "Close": 150.1604}, "2022-10-31": {"Open": 155.5714, "High": 155.4017, "Low": 151.6679, "Close": 153.2054}, "2022-10-28": {"Open": 145.1087, "High": 157.2387, "Low": 143.4516, "Close": 155.5714}, "2022-10-27": {"Open": 149.5514, "High": 149.2519, "Low": 135.7743, "Close": 145.1087}, "2022-10-26": {"Open": 150.6496, "High": 151.7378, "Low": 147.7944, "Close": 149.5514}, "2022-10-25": {"Open": 149.3418, "High": 152.247, "Low": 148.2536, "Close": 150.6496}, "2022-10-24": {"Open": 147.3351, "High": 149.9807, "Low": 145.3983, "Close": 149.3418}, "2022-10-21": {"Open": 142.4832, "High": 147.6026, "Low": 141.3351, "Close": 147.3351}, "2022-10-20": {"Open": 142.7627, "High": 145.6479, "Low": 141.7943, "Close": 142.4832}, "2022-10-19": {"Open": 144.6396, "High": 144.7087, "Low": 141.1454, "Close": 142.7627}, "2022-10-18": {"Open": 143.212, "High": 146.4566, "Low": 140.3767, "Close": 144.6396}, "2022-10-17": {"Open": 137.8509, "High": 145.009, "Low": 138.8392, "Close": 143.212}, "2022-10-14": {"Open": 142.593, "High": 144.42, "Low": 137.771, "Close": 137.8509}, "2022-10-13": {"Open": 138.38, "High": 143.3517, "Low": 132.979, "Close": 142.593}, "2022-10-12": {"Open": 139.009, "High": 140.3567, "Low": 137.9307, "Close": 138.38}, "2022-10-11": {"Open": 140.6862, "High": 141.1155, "Low": 137.9906, "Close": 139.009}, "2022-10-10": {"Open": 139.7877, "High": 141.6546, "Low": 138.343, "Close": 140.6862}, "2022-10-07": {"Open": 144.5398, "High": 145.009, "Low": 138.6695, "Close": 139.7877}, "2022-10-06": {"Open": 147.0656, "High": 147.2952, "Low": 143.9108, "Close": 144.5398}, "2022-10-05": {"Open": 145.7577, "High": 147.1554, "Low": 142.7727, "Close": 147.0656}, "2022-10-04": {"Open": 142.7328, "High": 145.9774, "Low": 144.0206, "Close": 145.7577}, "2022-10-03": {"Open": 137.2918, "High": 145.0289, "Low": 136.3434, "Close": 142.7328}, "2022-09-30": {"Open": 142.1737, "High": 143.3418, "Low": 136.1737, "Close": 137.2918}, "2022-09-29": {"Open": 149.1221, "High": 149.218, "Low": 140.4466, "Close": 142.1737}, "2022-09-28": {"Open": 151.6479, "High": 151.5082, "Low": 144.5997, "Close": 149.1221}, "2022-09-27": {"Open": 150.8493, "High": 154.4633, "Low": 146.2769, "Close": 151.6479}}, "AMZN": {"2022-11-04": {"Open": 89.31, "High": 92.44, "Low": 88.04, "Close": 91.16}, "2022-11-03": {"Open": 92.75, "High": 93.92, "Low": 89.02, "Close": 89.31}, "2022-11-02": {"Open": 96.81, "High": 97.74, "Low": 91.87, "Close": 92.75}, "2022-11-01": {"Open": 102.38, "High": 104.58, "Low": 96.06, "Close": 96.81}, "2022-10-31": {"Open": 103.89, "High": 104.87, "Low": 100.74, "Close": 102.38}, "2022-10-28": {"Open": 96.84, "High": 104.0, "Low": 94.81, "Close": 103.89}, "2022-10-27": {"Open": 115.8, "High": 116.01, "Low": 87.59, "Close": 96.84}, "2022-10-26": {"Open": 115.35, "High": 120.299, "Low": 114.11, "Close": 115.8}, "2022-10-25": {"Open": 119.06, "High": 121.3152, "Low": 114.75, "Close": 115.35}, "2022-10-24": {"Open": 119.85, "High": 121.08, "Low": 116.57, "Close": 119.06}, "2022-10-21": {"Open": 114.4, "High": 119.8, "Low": 113.2, "Close": 119.85}, "2022-10-20": {"Open": 114.2, "High": 118.24, "Low": 113.51, "Close": 114.4}, "2022-10-19": {"Open": 118.1, "High": 118.79, "Low": 113.22, "Close": 114.2}, "2022-10-18": {"Open": 115.12, "High": 119.52, "Low": 113.506, "Close": 118.1}, "2022-10-17": {"Open": 106.6, "High": 114.97, "Low": 106.52, "Close": 115.12}, "2022-10-14": {"Open": 112.2, "High": 114.96, "Low": 106.56, "Close": 106.6}, "2022-10-13": {"Open": 113.06, "High": 114.41, "Low": 105.345, "Close": 112.2}, "2022-10-12": {"Open": 112.25, "High": 113.87, "Low": 111.4, "Close": 113.06}, "2022-10-11": {"Open": 113.93, "High": 115.48, "Low": 110.39, "Close": 112.25}, "2022-10-10": {"Open": 114.55, "High": 116.25, "Low": 112.43, "Close": 113.93}, "2022-10-07": {"Open": 120.06, "High": 120.4, "Low": 113.88, "Close": 114.55}, "2022-10-06": {"Open": 121.7, "High": 121.88, "Low": 119.5, "Close": 120.06}, "2022-10-05": {"Open": 120.68, "High": 121.75, "Low": 117.69, "Close": 121.7}, "2022-10-04": {"Open": 116.37, "High": 123.0, "Low": 115.591, "Close": 120.68}, "2022-10-03": {"Open": 113.04, "High": 116.91, "Low": 111.78, "Close": 116.37}, "2022-09-30": {"Open": 115.1, "High": 116.92, "Low": 112.84, "Close": 113.04}, "2022-09-29": {"Open": 117.71, "High": 117.8, "Low": 113.06, "Close": 115.1}, "2022-09-28": {"Open": 114.59, "High": 118.7, "Low": 112.04, "Close": 117.71}, "2022-09-27": {"Open": 115.57, "High": 118.32, "Low": 113.05, "Close": 114.59}}}